AUTHORS.rst
CONTRIBUTING.rst
HISTORY.rst
LICENSE
MANIFEST.in
README.rst
setup.cfg
setup.py
commonutils/__init__.py
commonutils/cli.py
commonutils/commonutils.py
commonutils.egg-info/PKG-INFO
commonutils.egg-info/SOURCES.txt
commonutils.egg-info/dependency_links.txt
commonutils.egg-info/entry_points.txt
commonutils.egg-info/not-zip-safe
commonutils.egg-info/requires.txt
commonutils.egg-info/top_level.txt
docs/Makefile
docs/authors.rst
docs/conf.py
docs/contributing.rst
docs/history.rst
docs/index.rst
docs/installation.rst
docs/make.bat
docs/readme.rst
docs/usage.rst
tests/__init__.py
tests/test_commonutils.py