Metadata-Version: 1.1
Name: commonutils
Version: 0.1.0
Summary: some common utils
Home-page: https://github.com/lrbsunday/commonutils
Author: lrbsunday
Author-email: 272316131@qq.com
License: BSD license
Keywords: commonutils
Platform: UNKNOWN
Classifier: Development Status :: 2 - Pre-Alpha
Classifier: Intended Audience :: Developers
Classifier: License :: OSI Approved :: BSD License
Classifier: Natural Language :: English
Classifier: Programming Language :: Python :: 2
Classifier: Programming Language :: Python :: 2.6
Classifier: Programming Language :: Python :: 2.7
Classifier: Programming Language :: Python :: 3
Classifier: Programming Language :: Python :: 3.3
Classifier: Programming Language :: Python :: 3.4
Classifier: Programming Language :: Python :: 3.5
